<?xml version="1.0" encoding="UTF-8"?>
<!DOCTYPE mapper
	PUBLIC "-//mybatis.org//DTD Mapper 3.0//EN"
	"http://mybatis.org/dtd/mybatis-3-mapper.dtd">
<mapper namespace="mapper.TAK_PR_1200MTDTO">

	<!-- 가동현황용 생산데이터 -->
	<select id="pr_1100MT_NY" resultType="TAK_PR_1100MTDTO">
		select LIUN_NM,EQPM_OPRT_STTS_VAL
		from TB_PR_1100MT
		WHERE EQPM_OPRT_STTS_VAL = 'Y'
	</select>
	
	<!-- 싹싹 생산량 금일  -->
	<select id="pr_1100MT_SSG" resultType="TAK_PR_1100MTDTO">
		SELECT
		NVL(SUM(PROD_QNTT), 0) AS TOTAL_PROD_QNTT_SSG
		FROM
		TB_PR_1100MT
		WHERE ITEM_NM
		= '싹싹지우개'
		AND PROD_END_YN = 'Y'
		AND PROD_END_TIME IS NOT NULL
		AND
		TRUNC(TO_DATE(PROD_END_TIME, 'YYYY/MM/DD HH24:MI:SS')) =TRUNC(SYSDATE)
	</select>
	<!-- 하츄핑 생산량 금일  -->
	<select id="pr_1100MT_HH" resultType="TAK_PR_1100MTDTO">
		SELECT
		NVL(SUM(PROD_QNTT), 0) AS TOTAL_PROD_QNTT_HH
		FROM
		TB_PR_1100MT
		WHERE ITEM_NM
		= '하츄핑지우개'
		AND PROD_END_YN = 'Y'
		AND PROD_END_TIME IS NOT NULL
		AND
		TRUNC(TO_DATE(PROD_END_TIME, 'YYYY/MM/DD HH24:MI:SS')) =TRUNC(SYSDATE)
	</select>
	
	<!-- 싹싹 생산량 금주 A-1 -->
	<select id="pr_1100MT_SSG_week" resultType="TAK_PR_1100MTDTO">
		SELECT
		NVL(SUM(PROD_QNTT), 0) AS TOTAL_PROD_QNTT_SSG
		FROM
		TB_PR_1100MT
		WHERE ITEM_NM
		= '싹싹지우개'
		AND PROD_END_YN = 'Y'
		AND PROD_END_TIME IS NOT NULL
		AND
		TRUNC(TO_DATE(PROD_END_TIME, 'YYYY/MM/DD HH24:MI:SS'))
		BETWEEN TRUNC(SYSDATE - 6) AND TRUNC(SYSDATE)
	</select>
	<!-- 하츄핑 생산량 금주 A-1 -->
	<select id="pr_1100MT_HH_week" resultType="TAK_PR_1100MTDTO">
		SELECT
		NVL(SUM(PROD_QNTT), 0) AS TOTAL_PROD_QNTT_HH
		FROM
		TB_PR_1100MT
		WHERE ITEM_NM
		= '하츄핑지우개'
		AND PROD_END_YN = 'Y'
		AND PROD_END_TIME IS NOT NULL
		AND
		TRUNC(TO_DATE(PROD_END_TIME, 'YYYY/MM/DD HH24:MI:SS'))
		BETWEEN TRUNC(SYSDATE - 6) AND TRUNC(SYSDATE)
	</select>
	
	<!-- 싹싹 생산량 금월-->
	<select id="pr_1100MT_SSG_month"
		resultType="TAK_PR_1100MTDTO">
		SELECT NVL(SUM(PROD_QNTT), 0) AS TOTAL_PROD_QNTT_SSG
		FROM
		TB_PR_1100MT
		WHERE ITEM_NM
		= '싹싹지우개'
		AND PROD_END_YN = 'Y'
		AND
		PROD_END_TIME IS NOT NULL
		AND TRUNC(TO_DATE(PROD_END_TIME, 'YYYY/MM/DD
		HH24:MI:SS'))
		BETWEEN TRUNC(SYSDATE - 30) AND TRUNC(SYSDATE)
	</select>
	<!-- 하츄핑 생산량 금월 -->
	<select id="pr_1100MT_HH_month"
		resultType="TAK_PR_1100MTDTO">
		SELECT NVL(SUM(PROD_QNTT), 0) AS TOTAL_PROD_QNTT_HH
		FROM
		TB_PR_1100MT
		WHERE ITEM_NM
		= '하츄핑지우개'
		AND PROD_END_YN = 'Y'
		AND
		PROD_END_TIME IS NOT NULL
		AND TRUNC(TO_DATE(PROD_END_TIME, 'YYYY/MM/DD
		HH24:MI:SS'))
		BETWEEN TRUNC(SYSDATE - 30) AND TRUNC(SYSDATE)
	</select>
	

	<!--원형 그래프 데이터 총 월목표량 -->
	<select id="pr_1100MT_SS_IQ" resultType="TAK_PR_1100MTDTO">
		SELECT NVL(SUM(INDC_QNTT), 0) AS TOTAL_PROD_QNTT
		FROM
		TB_PR_1100MT
		WHERE PROD_END_YN = 'Y'
        AND PROD_END_TIME IS NOT NULL
		AND TRUNC(TO_DATE(PROD_END_TIME, 'YYYY/MM/DD HH24:MI:SS'))
		BETWEEN TRUNC(SYSDATE -30) AND TRUNC(SYSDATE)
	</select>
	
	
	<!--원형 그래프 데이터 총 월생산량 -->
	<select id="pr_1100MT_SS" resultType="TAK_PR_1100MTDTO">
		SELECT NVL(SUM(PROD_QNTT), 0) AS TOTAL_PROD_QNTT
		FROM
		TB_PR_1100MT
		WHERE PROD_END_YN = 'Y'
		AND
		PROD_END_TIME IS NOT NULL
		AND TRUNC(TO_DATE(PROD_END_TIME, 'YYYY/MM/DD HH24:MI:SS'))
		BETWEEN TRUNC(SYSDATE -30) AND TRUNC(SYSDATE)
	</select>
	
	<!--원형 그래프 데이터 총 월불량률 -->
	<select id="pr_1100MT_SS_DR" resultType="TAK_PR_1100MTDTO">
		SELECT
		NVL(SUM(PROD_QNTT), 0) AS TOTAL_PROD_QNTT,
		NVL(SUM(DFC_RT), 0) AS TOTAL_DFC_RT,
		ROUND(
		CASE
		WHEN NVL(SUM(PROD_QNTT), 0) = 0 THEN 0
		ELSE (NVL(SUM(DFC_RT), 0) / NVL(SUM(PROD_QNTT), 0)) * 100
		END,
		2
		) AS DEFECT_RATE
		FROM
		TB_PR_1100MT
		WHERE PROD_END_YN = 'Y'
		AND PROD_END_TIME IS NOT NULL
		AND TRUNC(TO_DATE(PROD_END_TIME, 'YYYY/MM/DD HH24:MI:SS'))
		BETWEEN TRUNC(SYSDATE - 30) AND TRUNC(SYSDATE)
	</select>
	
	
	<!-- 호기별 생산량 금일 A-1 -->
	<select id="pr_1100MT_lineA1" resultType="TAK_PR_1100MTDTO">
		SELECT
		NVL(SUM(PROD_QNTT), 0) AS TOTAL_PROD_QNTT
		FROM
		TB_PR_1100MT
		WHERE LIUN_NM
		= 'A라인1호기'
		AND PROD_END_YN = 'Y'
		AND PROD_END_TIME IS NOT NULL
		AND
		TRUNC(TO_DATE(PROD_END_TIME, 'YYYY/MM/DD HH24:MI:SS')) =TRUNC(SYSDATE)
	</select>
	<!-- 호기별 생산량 금일 A-2 -->
	<select id="pr_1100MT_lineA2" resultType="TAK_PR_1100MTDTO">
		SELECT
		NVL(SUM(PROD_QNTT), 0) AS TOTAL_PROD_QNTT
		FROM
		TB_PR_1100MT
		WHERE LIUN_NM
		= 'A라인2호기'
		AND PROD_END_YN = 'Y'
		AND PROD_END_TIME IS NOT NULL
		AND
		TRUNC(TO_DATE(PROD_END_TIME, 'YYYY/MM/DD HH24:MI:SS')) =TRUNC(SYSDATE)
	</select>
	<!-- 호기별 생산량 금일 A-3 -->
	<select id="pr_1100MT_lineA3" resultType="TAK_PR_1100MTDTO">
		SELECT
		NVL(SUM(PROD_QNTT), 0) AS TOTAL_PROD_QNTT
		FROM
		TB_PR_1100MT
		WHERE LIUN_NM
		= 'A라인3호기'
		AND PROD_END_YN = 'Y'
		AND PROD_END_TIME IS NOT NULL
		AND
		TRUNC(TO_DATE(PROD_END_TIME, 'YYYY/MM/DD HH24:MI:SS')) =TRUNC(SYSDATE)
	</select>

	<!-- 호기별 생산량 금일 B-1 -->
	<select id="pr_1100MT_lineB1" resultType="TAK_PR_1100MTDTO">
		SELECT
		NVL(SUM(PROD_QNTT), 0) AS TOTAL_PROD_QNTT
		FROM
		TB_PR_1100MT
		WHERE LIUN_NM
		= 'B라인1호기'
		AND PROD_END_YN = 'Y'
		AND PROD_END_TIME IS NOT NULL
		AND
		TRUNC(TO_DATE(PROD_END_TIME, 'YYYY/MM/DD HH24:MI:SS')) =TRUNC(SYSDATE)
	</select>
	<!-- 호기별 생산량 금일 B-2 -->
	<select id="pr_1100MT_lineB2" resultType="TAK_PR_1100MTDTO">
		SELECT
		NVL(SUM(PROD_QNTT), 0) AS TOTAL_PROD_QNTT
		FROM
		TB_PR_1100MT
		WHERE LIUN_NM
		= 'B라인2호기'
		AND PROD_END_YN = 'Y'
		AND PROD_END_TIME IS NOT NULL
		AND
		TRUNC(TO_DATE(PROD_END_TIME, 'YYYY/MM/DD HH24:MI:SS')) =TRUNC(SYSDATE)
	</select>
	<!-- 호기별 생산량 금일 B-3 -->
	<select id="pr_1100MT_lineB3" resultType="TAK_PR_1100MTDTO">
		SELECT
		NVL(SUM(PROD_QNTT), 0) AS TOTAL_PROD_QNTT
		FROM
		TB_PR_1100MT
		WHERE LIUN_NM
		= 'B라인3호기'
		AND PROD_END_YN = 'Y'
		AND PROD_END_TIME IS NOT NULL
		AND
		TRUNC(TO_DATE(PROD_END_TIME, 'YYYY/MM/DD HH24:MI:SS')) =TRUNC(SYSDATE)
	</select>

	<!-- 호기별 생산량 금일 C-1 -->
	<select id="pr_1100MT_lineC1" resultType="TAK_PR_1100MTDTO">
		SELECT
		NVL(SUM(PROD_QNTT), 0) AS TOTAL_PROD_QNTT
		FROM
		TB_PR_1100MT
		WHERE LIUN_NM
		= 'C라인1호기'
		AND PROD_END_YN = 'Y'
		AND PROD_END_TIME IS NOT NULL
		AND
		TRUNC(TO_DATE(PROD_END_TIME, 'YYYY/MM/DD HH24:MI:SS')) =TRUNC(SYSDATE)
	</select>
	<!-- 호기별 생산량 금일 C-2 -->
	<select id="pr_1100MT_lineC2" resultType="TAK_PR_1100MTDTO">
		SELECT
		NVL(SUM(PROD_QNTT), 0) AS TOTAL_PROD_QNTT
		FROM
		TB_PR_1100MT
		WHERE LIUN_NM
		= 'C라인2호기'
		AND PROD_END_YN = 'Y'
		AND PROD_END_TIME IS NOT NULL
		AND
		TRUNC(TO_DATE(PROD_END_TIME, 'YYYY/MM/DD HH24:MI:SS')) =TRUNC(SYSDATE)
	</select>
	<!-- 호기별 생산량 금일 C-3 -->
	<select id="pr_1100MT_lineC3" resultType="TAK_PR_1100MTDTO">
		SELECT
		NVL(SUM(PROD_QNTT), 0) AS TOTAL_PROD_QNTT
		FROM
		TB_PR_1100MT
		WHERE LIUN_NM
		= 'C라인3호기'
		AND PROD_END_YN = 'Y'
		AND PROD_END_TIME IS NOT NULL
		AND
		TRUNC(TO_DATE(PROD_END_TIME, 'YYYY/MM/DD HH24:MI:SS')) =TRUNC(SYSDATE)
	</select>


	<!-- 호기별 금주 생산량 -->


	<!-- 호기별 생산량 금주 A-1 -->
	<select id="pr_1100MT_lineA1_week" resultType="TAK_PR_1100MTDTO">
		SELECT
		NVL(SUM(PROD_QNTT), 0) AS TOTAL_PROD_QNTT
		FROM
		TB_PR_1100MT
		WHERE LIUN_NM
		= 'A라인1호기'
		AND PROD_END_YN = 'Y'
		AND PROD_END_TIME IS NOT NULL
		AND
		TRUNC(TO_DATE(PROD_END_TIME, 'YYYY/MM/DD HH24:MI:SS'))
		BETWEEN TRUNC(SYSDATE - 6) AND TRUNC(SYSDATE)
	</select>
	<!-- 호기별 생산량 금주 A-2 -->
	<select id="pr_1100MT_lineA2_week" resultType="TAK_PR_1100MTDTO">
		SELECT
		NVL(SUM(PROD_QNTT), 0) AS TOTAL_PROD_QNTT
		FROM
		TB_PR_1100MT
		WHERE LIUN_NM
		= 'A라인2호기'
		AND PROD_END_YN = 'Y'
		AND PROD_END_TIME IS NOT NULL
		AND
		TRUNC(TO_DATE(PROD_END_TIME, 'YYYY/MM/DD HH24:MI:SS'))
		BETWEEN TRUNC(SYSDATE - 6) AND TRUNC(SYSDATE)
	</select>
	<!-- 호기별 생산량 금주 A-3 -->
	<select id="pr_1100MT_lineA3_week" resultType="TAK_PR_1100MTDTO">
		SELECT
		NVL(SUM(PROD_QNTT), 0) AS TOTAL_PROD_QNTT
		FROM
		TB_PR_1100MT
		WHERE LIUN_NM
		= 'A라인3호기'
		AND PROD_END_YN = 'Y'
		AND PROD_END_TIME IS NOT NULL
		AND
		TRUNC(TO_DATE(PROD_END_TIME, 'YYYY/MM/DD HH24:MI:SS'))
		BETWEEN TRUNC(SYSDATE - 6) AND TRUNC(SYSDATE)
	</select>

	<!-- 호기별 생산량 금주 B-1 -->
	<select id="pr_1100MT_lineB1_week" resultType="TAK_PR_1100MTDTO">
		SELECT
		NVL(SUM(PROD_QNTT), 0) AS TOTAL_PROD_QNTT
		FROM
		TB_PR_1100MT
		WHERE LIUN_NM
		= 'B라인1호기'
		AND PROD_END_YN = 'Y'
		AND PROD_END_TIME IS NOT NULL
		AND
		TRUNC(TO_DATE(PROD_END_TIME, 'YYYY/MM/DD HH24:MI:SS'))
		BETWEEN TRUNC(SYSDATE - 6) AND TRUNC(SYSDATE)
	</select>
	<!-- 호기별 생산량 금주 B-2 -->
	<select id="pr_1100MT_lineB2_week" resultType="TAK_PR_1100MTDTO">
		SELECT
		NVL(SUM(PROD_QNTT), 0) AS TOTAL_PROD_QNTT
		FROM
		TB_PR_1100MT
		WHERE LIUN_NM
		= 'B라인2호기'
		AND PROD_END_YN = 'Y'
		AND PROD_END_TIME IS NOT NULL
		AND
		TRUNC(TO_DATE(PROD_END_TIME, 'YYYY/MM/DD HH24:MI:SS'))
		BETWEEN TRUNC(SYSDATE - 6) AND TRUNC(SYSDATE)
	</select>
	<!-- 호기별 생산량 금주 B-3 -->
	<select id="pr_1100MT_lineB3_week" resultType="TAK_PR_1100MTDTO">
		SELECT
		NVL(SUM(PROD_QNTT), 0) AS TOTAL_PROD_QNTT
		FROM
		TB_PR_1100MT
		WHERE LIUN_NM
		= 'B라인3호기'
		AND PROD_END_YN = 'Y'
		AND PROD_END_TIME IS NOT NULL
		AND
		TRUNC(TO_DATE(PROD_END_TIME, 'YYYY/MM/DD HH24:MI:SS'))
		BETWEEN TRUNC(SYSDATE - 6) AND TRUNC(SYSDATE)
	</select>

	<!-- 호기별 생산량 금주 C-1 -->
	<select id="pr_1100MT_lineC1_week" resultType="TAK_PR_1100MTDTO">
		SELECT
		NVL(SUM(PROD_QNTT), 0) AS TOTAL_PROD_QNTT
		FROM
		TB_PR_1100MT
		WHERE LIUN_NM
		= 'C라인1호기'
		AND PROD_END_YN = 'Y'
		AND PROD_END_TIME IS NOT NULL
		AND
		TRUNC(TO_DATE(PROD_END_TIME, 'YYYY/MM/DD HH24:MI:SS'))
		BETWEEN TRUNC(SYSDATE - 6) AND TRUNC(SYSDATE)
	</select>
	<!-- 호기별 생산량 금주 C-2 -->
	<select id="pr_1100MT_lineC2_week" resultType="TAK_PR_1100MTDTO">
		SELECT
		NVL(SUM(PROD_QNTT), 0) AS TOTAL_PROD_QNTT
		FROM
		TB_PR_1100MT
		WHERE LIUN_NM
		= 'C라인2호기'
		AND PROD_END_YN = 'Y'
		AND PROD_END_TIME IS NOT NULL
		AND
		TRUNC(TO_DATE(PROD_END_TIME, 'YYYY/MM/DD HH24:MI:SS'))
		BETWEEN TRUNC(SYSDATE - 6) AND TRUNC(SYSDATE)
	</select>
	<!-- 호기별 생산량 금주 C-3 -->
	<select id="pr_1100MT_lineC3_week" resultType="TAK_PR_1100MTDTO">
		SELECT
		NVL(SUM(PROD_QNTT), 0) AS TOTAL_PROD_QNTT
		FROM
		TB_PR_1100MT
		WHERE LIUN_NM
		= 'C라인3호기'
		AND PROD_END_YN = 'Y'
		AND PROD_END_TIME IS NOT NULL
		AND
		TRUNC(TO_DATE(PROD_END_TIME, 'YYYY/MM/DD HH24:MI:SS'))
		BETWEEN TRUNC(SYSDATE - 6) AND TRUNC(SYSDATE)
	</select>


	<!-- 호기별 금월 생산량 -->


	<!-- 호기별 생산량 금월 A-1 -->
	<select id="pr_1100MT_lineA1_month"
		resultType="TAK_PR_1100MTDTO">
		SELECT NVL(SUM(PROD_QNTT), 0) AS TOTAL_PROD_QNTT
		FROM
		TB_PR_1100MT
		WHERE LIUN_NM = 'A라인1호기'
		AND PROD_END_YN = 'Y'
		AND
		PROD_END_TIME IS NOT NULL
		AND TRUNC(TO_DATE(PROD_END_TIME, 'YYYY/MM/DD
		HH24:MI:SS'))
		BETWEEN TRUNC(SYSDATE - 30) AND TRUNC(SYSDATE)
	</select>
	<!-- 호기별 생산량 금월 A-2 -->
	<select id="pr_1100MT_lineA2_month"
		resultType="TAK_PR_1100MTDTO">
		SELECT NVL(SUM(PROD_QNTT), 0) AS TOTAL_PROD_QNTT
		FROM
		TB_PR_1100MT
		WHERE LIUN_NM = 'A라인2호기'
		AND PROD_END_YN = 'Y'
		AND
		PROD_END_TIME IS NOT NULL
		AND TRUNC(TO_DATE(PROD_END_TIME, 'YYYY/MM/DD
		HH24:MI:SS'))
		BETWEEN TRUNC(SYSDATE - 30) AND TRUNC(SYSDATE)
	</select>
	<!-- 호기별 생산량 금월 A-3 -->
	<select id="pr_1100MT_lineA3_month"
		resultType="TAK_PR_1100MTDTO">
		SELECT NVL(SUM(PROD_QNTT), 0) AS TOTAL_PROD_QNTT
		FROM
		TB_PR_1100MT
		WHERE LIUN_NM = 'A라인3호기'
		AND PROD_END_YN = 'Y'
		AND
		PROD_END_TIME IS NOT NULL
		AND TRUNC(TO_DATE(PROD_END_TIME, 'YYYY/MM/DD
		HH24:MI:SS'))
		BETWEEN TRUNC(SYSDATE - 30) AND TRUNC(SYSDATE)
	</select>

	<!-- 호기별 생산량 금월 B-1 -->
	<select id="pr_1100MT_lineB1_month"
		resultType="TAK_PR_1100MTDTO">
		SELECT NVL(SUM(PROD_QNTT), 0) AS TOTAL_PROD_QNTT
		FROM
		TB_PR_1100MT
		WHERE LIUN_NM = 'B라인1호기'
		AND PROD_END_YN = 'Y'
		AND
		PROD_END_TIME IS NOT NULL
		AND TRUNC(TO_DATE(PROD_END_TIME, 'YYYY/MM/DD
		HH24:MI:SS'))
		BETWEEN TRUNC(SYSDATE - 30) AND TRUNC(SYSDATE)
	</select>
	<!-- 호기별 생산량 금월 B-2 -->
	<select id="pr_1100MT_lineB2_month"
		resultType="TAK_PR_1100MTDTO">
		SELECT NVL(SUM(PROD_QNTT), 0) AS TOTAL_PROD_QNTT
		FROM
		TB_PR_1100MT
		WHERE LIUN_NM = 'B라인2호기'
		AND PROD_END_YN = 'Y'
		AND
		PROD_END_TIME IS NOT NULL
		AND TRUNC(TO_DATE(PROD_END_TIME, 'YYYY/MM/DD
		HH24:MI:SS'))
		BETWEEN TRUNC(SYSDATE - 30) AND TRUNC(SYSDATE)
	</select>
	<!-- 호기별 생산량 금월 B-3 -->
	<select id="pr_1100MT_lineB3_month"
		resultType="TAK_PR_1100MTDTO">
		SELECT NVL(SUM(PROD_QNTT), 0) AS TOTAL_PROD_QNTT
		FROM
		TB_PR_1100MT
		WHERE LIUN_NM = 'B라인3호기'
		AND PROD_END_YN = 'Y'
		AND
		PROD_END_TIME IS NOT NULL
		AND TRUNC(TO_DATE(PROD_END_TIME, 'YYYY/MM/DD
		HH24:MI:SS'))
		BETWEEN TRUNC(SYSDATE - 30) AND TRUNC(SYSDATE)
	</select>

	<!-- 호기별 생산량 금월 C-1 -->
	<select id="pr_1100MT_lineC1_month"
		resultType="TAK_PR_1100MTDTO">
		SELECT NVL(SUM(PROD_QNTT), 0) AS TOTAL_PROD_QNTT
		FROM
		TB_PR_1100MT
		WHERE LIUN_NM = 'C라인1호기'
		AND PROD_END_YN = 'Y'
		AND
		PROD_END_TIME IS NOT NULL
		AND TRUNC(TO_DATE(PROD_END_TIME, 'YYYY/MM/DD
		HH24:MI:SS'))
		BETWEEN TRUNC(SYSDATE - 30) AND TRUNC(SYSDATE)
	</select>
	<!-- 호기별 생산량 금월 C-2 -->
	<select id="pr_1100MT_lineC2_month"
		resultType="TAK_PR_1100MTDTO">
		SELECT NVL(SUM(PROD_QNTT), 0) AS TOTAL_PROD_QNTT
		FROM
		TB_PR_1100MT
		WHERE LIUN_NM = 'C라인2호기'
		AND PROD_END_YN = 'Y'
		AND
		PROD_END_TIME IS NOT NULL
		AND TRUNC(TO_DATE(PROD_END_TIME, 'YYYY/MM/DD
		HH24:MI:SS'))
		BETWEEN TRUNC(SYSDATE -30) AND TRUNC(SYSDATE)
	</select>
	<!-- 호기별 생산량 금월 C-3 -->
	<select id="pr_1100MT_lineC3_month"
		resultType="TAK_PR_1100MTDTO">
		SELECT NVL(SUM(PROD_QNTT), 0) AS TOTAL_PROD_QNTT
		FROM
		TB_PR_1100MT
		WHERE LIUN_NM = 'C라인3호기'
		AND PROD_END_YN = 'Y'
		AND
		PROD_END_TIME IS NOT NULL
		AND TRUNC(TO_DATE(PROD_END_TIME, 'YYYY/MM/DD
		HH24:MI:SS'))
		BETWEEN TRUNC(SYSDATE - 30) AND TRUNC(SYSDATE)
	</select>


	<!-- 호기별 금월 불량률 -->


	<!-- 호기별 불량률 금월 A-1 -->
	<select id="pr_1100MT_lineA1_month_DR"
		resultType="TAK_PR_1100MTDTO">
		SELECT
		NVL(SUM(PROD_QNTT), 0) AS TOTAL_PROD_QNTT,
		NVL(SUM(DFC_RT), 0) AS TOTAL_DFC_RT,
		ROUND(
		CASE
		WHEN NVL(SUM(PROD_QNTT), 0) = 0 THEN 0
		ELSE (NVL(SUM(DFC_RT), 0) / NVL(SUM(PROD_QNTT), 0)) * 100
		END,
		2
		) AS DEFECT_RATE
		FROM
		TB_PR_1100MT
		WHERE
		LIUN_NM = 'A라인1호기'
		AND PROD_END_YN = 'Y'
		AND PROD_END_TIME IS NOT NULL
		AND TRUNC(TO_DATE(PROD_END_TIME, 'YYYY/MM/DD HH24:MI:SS'))
		BETWEEN TRUNC(SYSDATE - 30) AND TRUNC(SYSDATE)
	</select>
	<!-- 호기별 불량률 금월 A-2 -->
	<select id="pr_1100MT_lineA2_month_DR"
		resultType="TAK_PR_1100MTDTO">
		SELECT
		NVL(SUM(PROD_QNTT), 0) AS TOTAL_PROD_QNTT,
		NVL(SUM(DFC_RT), 0) AS TOTAL_DFC_RT,
		ROUND(
		CASE
		WHEN NVL(SUM(PROD_QNTT), 0) = 0 THEN 0
		ELSE (NVL(SUM(DFC_RT), 0) / NVL(SUM(PROD_QNTT), 0)) * 100
		END,
		2
		) AS DEFECT_RATE
		FROM
		TB_PR_1100MT
		WHERE
		LIUN_NM = 'A라인2호기'
		AND PROD_END_YN = 'Y'
		AND PROD_END_TIME IS NOT NULL
		AND TRUNC(TO_DATE(PROD_END_TIME, 'YYYY/MM/DD HH24:MI:SS'))
		BETWEEN TRUNC(SYSDATE - 30) AND TRUNC(SYSDATE)
	</select>
	<!-- 호기별 불량률 금월 A-3 -->
	<select id="pr_1100MT_lineA3_month_DR"
		resultType="TAK_PR_1100MTDTO">
		SELECT
		NVL(SUM(PROD_QNTT), 0) AS TOTAL_PROD_QNTT,
		NVL(SUM(DFC_RT), 0) AS TOTAL_DFC_RT,
		ROUND(
		CASE
		WHEN NVL(SUM(PROD_QNTT), 0) = 0 THEN 0
		ELSE (NVL(SUM(DFC_RT), 0) / NVL(SUM(PROD_QNTT), 0)) * 100
		END,
		2
		) AS DEFECT_RATE
		FROM
		TB_PR_1100MT
		WHERE
		LIUN_NM = 'A라인3호기'
		AND PROD_END_YN = 'Y'
		AND PROD_END_TIME IS NOT NULL
		AND TRUNC(TO_DATE(PROD_END_TIME, 'YYYY/MM/DD HH24:MI:SS'))
		BETWEEN TRUNC(SYSDATE - 30) AND TRUNC(SYSDATE)
	</select>

	<!-- 호기별 불량률 금월 B-1 -->
	<select id="pr_1100MT_lineB1_month_DR"
		resultType="TAK_PR_1100MTDTO">
		SELECT
		NVL(SUM(PROD_QNTT), 0) AS TOTAL_PROD_QNTT,
		NVL(SUM(DFC_RT), 0) AS TOTAL_DFC_RT,
		ROUND(
		CASE
		WHEN NVL(SUM(PROD_QNTT), 0) = 0 THEN 0
		ELSE (NVL(SUM(DFC_RT), 0) / NVL(SUM(PROD_QNTT), 0)) * 100
		END,
		2
		) AS DEFECT_RATE
		FROM
		TB_PR_1100MT
		WHERE
		LIUN_NM = 'B라인1호기'
		AND PROD_END_YN = 'Y'
		AND PROD_END_TIME IS NOT NULL
		AND TRUNC(TO_DATE(PROD_END_TIME, 'YYYY/MM/DD HH24:MI:SS'))
		BETWEEN TRUNC(SYSDATE - 30) AND TRUNC(SYSDATE)
	</select>
	<!-- 호기별 불량률 금월 B-2 -->
	<select id="pr_1100MT_lineB2_month_DR"
		resultType="TAK_PR_1100MTDTO">
		SELECT
		NVL(SUM(PROD_QNTT), 0) AS TOTAL_PROD_QNTT,
		NVL(SUM(DFC_RT), 0) AS TOTAL_DFC_RT,
		ROUND(
		CASE
		WHEN NVL(SUM(PROD_QNTT), 0) = 0 THEN 0
		ELSE (NVL(SUM(DFC_RT), 0) / NVL(SUM(PROD_QNTT), 0)) * 100
		END,
		2
		) AS DEFECT_RATE
		FROM
		TB_PR_1100MT
		WHERE
		LIUN_NM = 'B라인2호기'
		AND PROD_END_YN = 'Y'
		AND PROD_END_TIME IS NOT NULL
		AND TRUNC(TO_DATE(PROD_END_TIME, 'YYYY/MM/DD HH24:MI:SS'))
		BETWEEN TRUNC(SYSDATE - 30) AND TRUNC(SYSDATE)
	</select>
	<!-- 호기별 불량률 금월 B-3 -->
	<select id="pr_1100MT_lineB3_month_DR"
		resultType="TAK_PR_1100MTDTO">
		SELECT
		NVL(SUM(PROD_QNTT), 0) AS TOTAL_PROD_QNTT,
		NVL(SUM(DFC_RT), 0) AS TOTAL_DFC_RT,
		ROUND(
		CASE
		WHEN NVL(SUM(PROD_QNTT), 0) = 0 THEN 0
		ELSE (NVL(SUM(DFC_RT), 0) / NVL(SUM(PROD_QNTT), 0)) * 100
		END,
		2
		) AS DEFECT_RATE
		FROM
		TB_PR_1100MT
		WHERE
		LIUN_NM = 'B라인3호기'
		AND PROD_END_YN = 'Y'
		AND PROD_END_TIME IS NOT NULL
		AND TRUNC(TO_DATE(PROD_END_TIME, 'YYYY/MM/DD HH24:MI:SS'))
		BETWEEN TRUNC(SYSDATE - 30) AND TRUNC(SYSDATE)
	</select>

	<!-- 호기별 불량률 금월 C-1 -->
	<select id="pr_1100MT_lineC1_month_DR"
		resultType="TAK_PR_1100MTDTO">
		SELECT
		NVL(SUM(PROD_QNTT), 0) AS TOTAL_PROD_QNTT,
		NVL(SUM(DFC_RT), 0) AS TOTAL_DFC_RT,
		ROUND(
		CASE
		WHEN NVL(SUM(PROD_QNTT), 0) = 0 THEN 0
		ELSE (NVL(SUM(DFC_RT), 0) / NVL(SUM(PROD_QNTT), 0)) * 100
		END,
		2
		) AS DEFECT_RATE
		FROM
		TB_PR_1100MT
		WHERE
		LIUN_NM = 'C라인1호기'
		AND PROD_END_YN = 'Y'
		AND PROD_END_TIME IS NOT NULL
		AND TRUNC(TO_DATE(PROD_END_TIME, 'YYYY/MM/DD HH24:MI:SS'))
		BETWEEN TRUNC(SYSDATE - 30) AND TRUNC(SYSDATE)
	</select>
	<!-- 호기별 불량률 금월 C-2 -->
	<select id="pr_1100MT_lineC2_month_DR"
		resultType="TAK_PR_1100MTDTO">
		SELECT
		NVL(SUM(PROD_QNTT), 0) AS TOTAL_PROD_QNTT,
		NVL(SUM(DFC_RT), 0) AS TOTAL_DFC_RT,
		ROUND(
		CASE
		WHEN NVL(SUM(PROD_QNTT), 0) = 0 THEN 0
		ELSE (NVL(SUM(DFC_RT), 0) / NVL(SUM(PROD_QNTT), 0)) * 100
		END,
		2
		) AS DEFECT_RATE
		FROM
		TB_PR_1100MT
		WHERE
		LIUN_NM = 'C라인2호기'
		AND PROD_END_YN = 'Y'
		AND PROD_END_TIME IS NOT NULL
		AND TRUNC(TO_DATE(PROD_END_TIME, 'YYYY/MM/DD HH24:MI:SS'))
		BETWEEN TRUNC(SYSDATE - 30) AND TRUNC(SYSDATE)
	</select>
	<!-- 호기별 불량률 금월 C-3 -->
	<select id="pr_1100MT_lineC3_month_DR"
		resultType="TAK_PR_1100MTDTO">
		SELECT
		NVL(SUM(PROD_QNTT), 0) AS TOTAL_PROD_QNTT,
		NVL(SUM(DFC_RT), 0) AS TOTAL_DFC_RT,
		ROUND(
		CASE
		WHEN NVL(SUM(PROD_QNTT), 0) = 0 THEN 0
		ELSE (NVL(SUM(DFC_RT), 0) / NVL(SUM(PROD_QNTT), 0)) * 100
		END,
		2
		) AS DEFECT_RATE
		FROM
		TB_PR_1100MT
		WHERE
		LIUN_NM = 'C라인3호기'
		AND PROD_END_YN = 'Y'
		AND PROD_END_TIME IS NOT NULL
		AND TRUNC(TO_DATE(PROD_END_TIME, 'YYYY/MM/DD HH24:MI:SS'))
		BETWEEN TRUNC(SYSDATE - 30) AND TRUNC(SYSDATE)
	</select>



</mapper>